tests/__init__.py
tests/data.py
tests/indicator.py
tests/test_widget.py
vnpy_chart/__init__.py
vnpy_chart/axis.py
vnpy_chart/base.py
vnpy_chart/manager.py
vnpy_chart/widget.py
vnpy_chart/assets/smiley_face.png
vnpy_chart/items/__init__.py
vnpy_chart/items/candle_item.py
vnpy_chart/items/chart_item.py
vnpy_chart/items/icon_item.py
vnpy_chart/items/line_item.py
vnpy_chart/items/utils.py
vnpy_chart/items/volume_item.py
vnpy_chart-0.0.5.dist-info/METADATA
vnpy_chart-0.0.5.dist-info/WHEEL
vnpy_chart-0.0.5.dist-info/top_level.txt
vnpy_chart-0.0.5.dist-info/RECORD
