Metadata-Version: 2.1
Name: vnpy_chart
Version: 0.0.5
Summary: enhanced chart for vnpy.
Home-page: https://github.com/suyu0925/vnpy_chart
Author: suyu0925
Author-email: suyu0925@gmail.com
License: MIT
Keywords: quant,quantitative,investment,trading,algotrading
Classifier: Development Status :: 5 - Production/Stable
Classifier: Operating System :: Microsoft :: Windows
Classifier: Operating System :: POSIX :: Linux
Classifier: Operating System :: MacOS
Classifier: Programming Language :: Python :: 3
Classifier: Programming Language :: Python :: 3.10
Classifier: Programming Language :: Python :: 3.11
Classifier: Programming Language :: Python :: 3.12
Classifier: Topic :: Office/Business :: Financial :: Investment
Classifier: License :: OSI Approved :: MIT License
Classifier: Natural Language :: Chinese (Simplified)
Requires-Dist: vnpy
